nicecoding/__init__.py
nicecoding/password_make.py
worigip-0.0.2.dist-info/METADATA
worigip-0.0.2.dist-info/WHEEL
worigip-0.0.2.dist-info/top_level.txt
worigip-0.0.2.dist-info/RECORD
